{
  "deterministic": false,
  "confidenceInterval": 90,
  "skills": {
    "Triumphant Pulse": {
      "discount": 10,
      "default": 10
    },
    "Shadow Break": {
      "discount": null
    },
    "Behold Thine Emperor's Divine Might": {
      "discount": null
    },
    "Let's Pump Some Iron!": {
      "discount": 10
    },
    "Standing By": {
      "discount": null,
      "default": 0
    },
    "Nemesis": {
      "discount": null
    },
    "Professor of Curvature": {
      "discount": null,
      "default": 10
    },
    "Corner Adept ○": {
      "discount": null,
      "default": 0
    },
    "Long Straightaways": {
      "discount": null
    },
    "Long Corners": {
      "discount": 35
    },
    "Passing Pro": {
      "discount": 30
    },
    "Pressure": {
      "discount": 10
    },
    "After-School Stroll": {
      "discount": null
    },
    "Levelheaded": {
      "discount": null
    },
    "Intense Gaze": {
      "discount": 10
    },
    "Corner Recovery": {
      "discount": null,
      "default": 0
    },
    "Highlander": {
      "discount": null
    },
    "Uma Stan": {
      "discount": null
    },
    "Non-Standard Distance": {
      "discount": null
    },
    "Ramp Up": {
      "discount": 0,
      "default": 0
    },
    "Right-Handed": {
      "discount": null
    },
    "Slipstream": {
      "discount": null
    },
    "End Closer Corners": {
      "discount": null
    },
    "Ignited Spirit SPD": {
      "discount": 30
    },
    "Stamina Eater": {
      "discount": null
    },
    "Swinging Maestro": {
      "discount": null,
      "default": 10
    },
    "Rushing Gale!": {
      "discount": 30,
      "default": 10
    },
    "Straightaway Acceleration": {
      "discount": 0,
      "default": 0
    },
    "Straightaway Recovery": {
      "discount": null
    },
    "It's On!": {
      "discount": 10,
      "default": 10
    },
    "No Stopping Me!": {
      "discount": 35,
      "default": 10
    },
    "Nimble Navigator": {
      "discount": 0,
      "default": 0
    },
    "Deep Breaths": {
      "discount": 30
    },
    "Firm Conditions": {
      "discount": null
    },
    "Extra Tank": {
      "discount": 10
    },
    "End Closer Savvy": {
      "discount": 30
    },
    "Burning Spirit SPD": {
      "discount": null
    },
    "Long Straightaways ◎": {
      "discount": null
    },
    "Long Straightaways ○": {
      "discount": null
    },
    "Long Corners ◎": {
      "discount": 35
    },
    "Long Corners ○": {
      "discount": 35
    },
    "Non-Standard Distance ◎": {
      "discount": null
    },
    "Non-Standard Distance ○": {
      "discount": null
    },
    "Right-Handed ◎": {
      "discount": null
    },
    "Right-Handed ○": {
      "discount": null
    },
    "End Closer Corners ◎": {
      "discount": null
    },
    "End Closer Corners ○": {
      "discount": null
    },
    "Firm Conditions ◎": {
      "discount": null
    },
    "Firm Conditions ○": {
      "discount": null
    },
    "End Closer Savvy ◎": {
      "discount": 30
    },
    "End Closer Savvy ○": {
      "discount": 30
    },
    "Lay Low": {
      "discount": null
    },
    "End Closer Straightaways": {
      "discount": 0,
      "default": 0
    },
    "End Closer Straightaways ◎": {
      "discount": 0,
      "default": 0
    },
    "End Closer Straightaways ○": {
      "discount": 0,
      "default": 0
    },
    "The Duty of Dignity Calls": {
      "discount": null
    },
    "Competitive Spirit": {
      "discount": 10
    },
    "Competitive Spirit ◎": {
      "discount": 10
    },
    "Competitive Spirit ○": {
      "discount": 10
    },
    "Straightaway Spurt": {
      "discount": null,
      "default": 0
    },
    "This Dance Is for Vittoria!": {
      "discount": null
    },
    "Sleeping Lion": {
      "discount": null,
      "default": 0
    },
    "Encroaching Shadow": {
      "discount": null,
      "default": 0
    },
    "Lone Wolf": {
      "discount": 0,
      "default": 0
    },
    "Homestretch Haste": {
      "discount": 30
    },
    "Inside Scoop": {
      "discount": null
    },
    "Anchors Aweigh!": {
      "discount": 10,
      "default": 10
    },
    "Straightaway Adept": {
      "discount": null
    },
    "Focus": {
      "discount": 30
    },
    "Early Start": {
      "discount": null
    },
    "Masterful Gambit": {
      "discount": 30
    }
  },
  "track": {
    "courseId": "",
    "distance": 3000,
    "groundCondition": "Firm",
    "numUmas": 9,
    "season": "Fall",
    "trackName": "Kyoto",
    "weather": "Sunny",
    "surface": "Turf"
  },
  "uma": {
    "distanceAptitude": "S",
    "guts": 488,
    "power": 840,
    "mood": null,
    "skills": [
      "Swinging Maestro",
      "Sleeping Lion",
      "Professor of Curvature",
      "Long Corners ○",
      "Encroaching Shadow",
      "Straightaway Recovery"
    ],
    "speed": 1151,
    "stamina": 1100,
    "strategy": "End Closer",
    "styleAptitude": "A",
    "surfaceAptitude": "A",
    "unique": "Nemesis",
    "wisdom": 553
  }
}
